{
  "main": {
    "name":"Hashirr Lukmahn",

    "description":"I am a web development engineer and I use react and vue.js to develop pages. This project is a resume template that can be used as the project home page or resume page",
    "image":"Hashirr-Picture.jpg",
    "bio":"Use this bio section as your way of describing yourself and saying what you do, what technologies you like to use or feel most comfortable with, describing your personality, or whatever else you feel like throwing in.",
    "contactmessage":"Here is where you should write your message to readers to have them get in contact with you.",
    "email": "hashirr_7@hotmail.com",
    "phone": "720-314-4312",
    "github":"https://github.com/HashirrLukmahn?tab=repositories",
    "project":"https://github.com/nordicgiant2/react-nice-resume",
    "address":{
      "street":"1421 Begonia Way",
      "city":"Superior",
      "state":"Colorado",
      "zip": "80027"
    },
    "website": "http://www.timbakerdev.com",
    "resumedownload":"http://timbakerdev.com",
    "social":[
      {
        "name":"facebook",
        "url":"https://github.com/nordicgiant2/react-nice-resume",
        "className":"fa fa-facebook"
      },
      {
        "name":"twitter",
        "url":"http://twitter.com",
        "className":"fa fa-twitter"
      },
      {
        "name":"linkedin",
        "url":"https://www.linkedin.com/in/hashirr-lukmahn/",
        "className":"fa fa-linkedin"
      },
      {
        "name":"instagram",
        "url":"https://www.instagram.com/hashbrownpls/",
        "className":"fa fa-instagram"
      },
      {
        "name":"github",
        "url":"https://github.com/nordicgiant2/react-nice-resume",
        "className":"fa fa-github"
      }
    ]
  },
  "resume":{
    "skillmessage":"Here you can create a short write-up of your skills to show off to employers",
    "education":[
      {
        "school":"University of Colorado in Boulder",
        "degree":"Bachelors of Science in Computer Science",
        "graduated":"August 2022 - December 2024",
        "description":"Describe your experience at school, what you learned, what useful skills you have acquired etc."
      },
      {
        "school":"Temasek Polytechnic (Singapore)",
        "degree":"Diploma in Information Technology",
        "graduated":"April 2016 - April 2019",
        "description":"Describe your experience at school, what you learned, what useful skills you have acquired etc."
      }
    ],
    "work":[
      {
        "company":"Research and Innovation Office, University of Colorado Boulder",
        "title":"AI Developer Intern",
        "years":"June 2024 - September 2024",
        "description":"Describe work, special projects, notable achievements, what technologies you have been working with, and anything else that would be useful for an employer to know."
      },
      {
        "company":"Partners Group Singapore Private Limited",
        "title":"Junior Application Specialist",
        "years":"March 2017 - February 2018",
        "description":"Describe work, special projects, notable achievements, what technologies you have been working with, and anything else that would be useful for an employer to know."
      },
      {
        "company":"Singapore Police Force",
        "title:":"Assistant Technical Officer",
        "years":"October 2019 - October 2021",
        "description":"Describe work, special projects, notable achievements, what technologies you have been working with, and anything else that would be useful for an employer to know."
      },
      {
        "company":"A-Smart Life Private Limited",
        "title:":"Product Developer Intern",
        "years":"July 2018 - May 2019",
        "description":"Describe work, special projects, notable achievements, what technologies you have been working with, and anything else that would be useful for an employer to know."
      }

    ],
    "skills":[
      {
        "name":"Python",
        "level":"60%"
      },
      {
        "name":"AngularJS",
        "level":"60%"
      },
      {
        "name":"React.js/React Native",
        "level":"90%"
      },
      {
        "name":"CSS",
        "level":"50%"
      },
      {
        "name":"JavaScript",
        "level":"80%"
      },
      {
        "name":"Android Studio",
        "level":"70%"
      },
      {
        "name":"JAVA",
        "level":"80%"
      }
    ]
  },
  "portfolio":{
    "projects": [
      {
        "title":"Canadian Wanderlust",
        "category":"My Travel Blog for my post-university travels",
        "image":"01.jpg",
        "url":"https://www.canadianwanderlust.com"
      },
      {
        "title":"Fury Fighting Gear",
        "category":"(offline now) A fighting gear company I started",
        "image":"02.jpg",
        "url":"http://www.timbakerdev.com"
      },
      {
        "title":"Original Thai Food",
        "category":"Website I built for a restaurant I like in Thailand",
        "image":"03.jpg",
        "url":"http://www.timbakerdev.com/originalthaifood.github.io"
      },
      {
        "title":"Resume Website",
        "category":"A React based resume website template",
        "image":"04.jpg",
        "url":"http://www.timbakerdev.com"
      },
      {
        "title":"Smirkspace",
        "category":"(MVP Only) A React and Meteor based chat University project.",
        "image":"05.jpg",
        "url":"http://www.smirkspace.com"
      },
      {
        "title":"Canadian Wanderlust",
        "category":"My Travel Blog for my post-university travels",
        "image":"06.jpg",
        "url":"https://www.canadianwanderlust.com"
      },
      {
        "title":"Fury Fighting Gear",
        "category":"(offline now) A fighting gear company I started",
        "image":"01.jpg",
        "url":"http://www.timbakerdev.com"
      },
      {
        "title":"Original Thai Food",
        "category":"Website I built for a restaurant I like in Thailand",
        "image":"02.jpg",
        "url":"http://www.timbakerdev.com/originalthaifood.github.io"
      },
      {
        "title":"Original Thai Food",
        "category":"Website I built for a restaurant I like in Thailand",
        "image":"03.jpg",
        "url":"http://www.timbakerdev.com/originalthaifood.github.io"
      },
      {
        "title":"Resume Website",
        "category":"A React based resume website template",
        "image":"04.jpg",
        "url":"http://www.timbakerdev.com"
      },
      {
        "title":"Smirkspace",
        "category":"(MVP Only) A React and Meteor based chat University project.",
        "image":"05.jpg",
        "url":"http://www.smirkspace.com"
      },
      {
        "title":"Canadian Wanderlust",
        "category":"My Travel Blog for my post-university travels",
        "image":"06.jpg",
        "url":"https://www.canadianwanderlust.com"
      }
    ]
  }
}
